ramldocgen/__init__.py
ramldocgen/__main__.py
ramldocgen/generator.py
ramldocgen/inlines.py
ramldocgen/ramldocgen.py
ramldocgen-1.0.1.dist-info/DESCRIPTION.rst
ramldocgen-1.0.1.dist-info/METADATA
ramldocgen-1.0.1.dist-info/RECORD
ramldocgen-1.0.1.dist-info/WHEEL
ramldocgen-1.0.1.dist-info/entry_points.txt
ramldocgen-1.0.1.dist-info/metadata.json
ramldocgen-1.0.1.dist-info/top_level.txt
