Metadata-Version: 2.0
Name: ramldocgen
Version: 1.0.1
Summary: Python based command line interface tool for generating HTML content from RAML documentation.
Home-page: https://github.com/baliame/ramldocgen
Author: Baliame
Author-email: akos.toth@cheppers.com
License: MIT
Keywords: raml api documentation generator
Platform: UNKNOWN
Classifier: Development Status :: 4 - Beta
Classifier: Environment :: Console
Classifier: Intended Audience :: Developers
Classifier: License :: OSI Approved :: MIT License
Classifier: Programming Language :: Python :: 3
Classifier: Programming Language :: Python :: 3.2
Classifier: Programming Language :: Python :: 3.3
Classifier: Programming Language :: Python :: 3.4
Classifier: Programming Language :: Python :: 3.5
Classifier: Topic :: Documentation
Classifier: Topic :: Software Development :: Documentation
Classifier: Topic :: Utilities
Requires-Dist: click
Requires-Dist: pyraml-parser
